flask_admin/__init__.py
flask_admin/_backwards.py
flask_admin/_compat.py
flask_admin/actions.py
flask_admin/babel.py
flask_admin/base.py
flask_admin/consts.py
flask_admin/helpers.py
flask_admin/menu.py
flask_admin/tools.py
flask_admin/contrib/__init__.py
flask_admin/contrib/rediscli.py
flask_admin/contrib/appengine/__init__.py
flask_admin/contrib/appengine/fields.py
flask_admin/contrib/appengine/form.py
flask_admin/contrib/appengine/view.py
flask_admin/contrib/fileadmin/__init__.py
flask_admin/contrib/fileadmin/azure.py
flask_admin/contrib/fileadmin/s3.py
flask_admin/contrib/geoa/__init__.py
flask_admin/contrib/geoa/fields.py
flask_admin/contrib/geoa/form.py
flask_admin/contrib/geoa/typefmt.py
flask_admin/contrib/geoa/view.py
flask_admin/contrib/geoa/widgets.py
flask_admin/contrib/mongoengine/__init__.py
flask_admin/contrib/mongoengine/ajax.py
flask_admin/contrib/mongoengine/fields.py
flask_admin/contrib/mongoengine/filters.py
flask_admin/contrib/mongoengine/form.py
flask_admin/contrib/mongoengine/helpers.py
flask_admin/contrib/mongoengine/subdoc.py
flask_admin/contrib/mongoengine/tools.py
flask_admin/contrib/mongoengine/typefmt.py
flask_admin/contrib/mongoengine/view.py
flask_admin/contrib/mongoengine/widgets.py
flask_admin/contrib/peewee/__init__.py
flask_admin/contrib/peewee/ajax.py
flask_admin/contrib/peewee/filters.py
flask_admin/contrib/peewee/form.py
flask_admin/contrib/peewee/tools.py
flask_admin/contrib/peewee/view.py
flask_admin/contrib/peeweemodel/__init__.py
flask_admin/contrib/pymongo/__init__.py
flask_admin/contrib/pymongo/filters.py
flask_admin/contrib/pymongo/tools.py
flask_admin/contrib/pymongo/typefmt.py
flask_admin/contrib/pymongo/view.py
flask_admin/contrib/sqla/__init__.py
flask_admin/contrib/sqla/ajax.py
flask_admin/contrib/sqla/fields.py
flask_admin/contrib/sqla/filters.py
flask_admin/contrib/sqla/form.py
flask_admin/contrib/sqla/tools.py
flask_admin/contrib/sqla/typefmt.py
flask_admin/contrib/sqla/validators.py
oy_libs_Flask_Admin-1.5.3.dist-info/AUTHORS
oy_libs_Flask_Admin-1.5.3.dist-info/LICENSE
oy_libs_Flask_Admin-1.5.3.dist-info/METADATA
oy_libs_Flask_Admin-1.5.3.dist-info/NOTICE
oy_libs_Flask_Admin-1.5.3.dist-info/WHEEL
oy_libs_Flask_Admin-1.5.3.dist-info/top_level.txt
oy_libs_Flask_Admin-1.5.3.dist-info/RECORD
