Metadata-Version: 2.1
Name: oy-libs-Flask-Admin
Version: 1.5.3
Summary: Simple and extensible admin interface framework for Flask
Home-page: https://github.com/flask-admin/flask-admin/
Author: Flask-Admin team
Author-email: serge.koval+github@gmail.com
License: BSD
Platform: any
Classifier: Development Status :: 4 - Beta
Classifier: Environment :: Web Environment
Classifier: Intended Audience :: Developers
Classifier: License :: OSI Approved :: BSD License
Classifier: Operating System :: OS Independent
Classifier: Programming Language :: Python
Classifier: Topic :: Software Development :: Libraries :: Python Modules
Classifier: Programming Language :: Python :: 2.7
Classifier: Programming Language :: Python :: 3.3
Classifier: Programming Language :: Python :: 3.4
Classifier: Programming Language :: Python :: 3.5
Classifier: Programming Language :: Python :: 3.6
Requires-Dist: Flask (>=0.7)
Requires-Dist: wtforms
Provides-Extra: aws
Requires-Dist: boto ; extra == 'aws'
Provides-Extra: azure
Requires-Dist: azure-storage-blob ; extra == 'azure'
